pyannoy/__init__.py
pyannoy-1.1.0.dist-info/METADATA
pyannoy-1.1.0.dist-info/WHEEL
pyannoy-1.1.0.dist-info/entry_points.txt
pyannoy-1.1.0.dist-info/licenses/LICENSE
pyannoy-1.1.0.dist-info/RECORD
