Metadata-Version: 2.4
Name: pyannoy
Version: 1.1.0
Summary: An annoying Python package
Author-email: Nguyen Son Linh <linhns59@gmail.com>
License-File: LICENSE
Requires-Python: >=3.11
